MANIFEST.in
README.rst
ez_setup.py
requirements-test.txt
requirements.txt
setup.py
Heralding.egg-info/PKG-INFO
Heralding.egg-info/SOURCES.txt
Heralding.egg-info/dependency_links.txt
Heralding.egg-info/requires.txt
Heralding.egg-info/top_level.txt
bin/heralding
heralding/__init__.py
heralding/heralding.yml
heralding/honeypot.py
heralding/wordlist.txt
heralding/__pycache__/__init__.cpython-37.pyc
heralding/capabilities/__init__.py
heralding/capabilities/ftp.py
heralding/capabilities/handlerbase.py
heralding/capabilities/http.py
heralding/capabilities/https.py
heralding/capabilities/imap.py
heralding/capabilities/imaps.py
heralding/capabilities/mysql.py
heralding/capabilities/pop3.py
heralding/capabilities/pop3s.py
heralding/capabilities/postgresql.py
heralding/capabilities/rdp.py
heralding/capabilities/smtp.py
heralding/capabilities/smtps.py
heralding/capabilities/socks5.py
heralding/capabilities/ssh.py
heralding/capabilities/telnet.py
heralding/capabilities/vnc.py
heralding/libs/__init__.py
heralding/libs/aiobaserequest.py
heralding/libs/cracker/vnc.py
heralding/libs/http/__init__.py
heralding/libs/http/aioclient.py
heralding/libs/http/aioserver.py
heralding/libs/msrdp/__init__.py
heralding/libs/msrdp/packer.py
heralding/libs/msrdp/parser.py
heralding/libs/msrdp/pdu.py
heralding/libs/msrdp/security.py
heralding/libs/msrdp/tls.py
heralding/libs/telnetsrv/__init__.py
heralding/libs/telnetsrv/telnetsrvlib.py
heralding/misc/__init__.py
heralding/misc/common.py
heralding/misc/session.py
heralding/misc/socket_names.py
heralding/reporting/__init__.py
heralding/reporting/base_logger.py
heralding/reporting/curiosum_integration.py
heralding/reporting/file_logger.py
heralding/reporting/hpfeeds_logger.py
heralding/reporting/reporting_relay.py
heralding/reporting/syslog_logger.py
heralding/tests/__init__.py
heralding/tests/test_config.py
heralding/tests/test_encoding.py
heralding/tests/test_ftp.py
heralding/tests/test_hpfeeds.py
heralding/tests/test_http.py
heralding/tests/test_imap.py
heralding/tests/test_mysql.py
heralding/tests/test_pop3.py
heralding/tests/test_postgresql.py
heralding/tests/test_rdp.py
heralding/tests/test_smtp.py
