Metadata-Version: 1.0
Name: Heralding
Version: 1.0.7
Summary: Credentials catching honeypot.
Home-page: https://github.com/johnnykv/heralding
Author: Johnny Vestergaard
Author-email: jkv@unixcluster.dk
License: GPL 3
Platform: UNKNOWN
